can_source/__init__.py
can_source/can_const.py
can_source/can_import.py
can_source/can_sys.py
can_source/cantonese.py
can_source/can_ast/__init__.py
can_source/can_ast/can_exp.py
can_source/can_ast/can_macro_node.py
can_source/can_ast/can_stat.py
can_source/can_compiler/compiler.py
can_source/can_compiler/lib_gen_helper.py
can_source/can_context/__init__.py
can_source/can_context/macros.py
can_source/can_context/parsers.py
can_source/can_context/tokens.py
can_source/can_error/__init__.py
can_source/can_error/compile_time.py
can_source/can_error/runtime.py
can_source/can_lexer/__init__.py
can_source/can_lexer/can_keywords.py
can_source/can_lexer/can_lexer.py
can_source/can_lexer/can_token.py
can_source/can_lexer/pos.py
can_source/can_libs/README.md
can_source/can_libs/__init__.py
can_source/can_libs/lib_gobals.py
can_source/can_libs/std/__init__.py
can_source/can_libs/std/impl.py
can_source/can_libs/std/app/__init__.py
can_source/can_libs/std/app/impl.py
can_source/can_libs/std/csv/__init__.py
can_source/can_libs/std/csv/impl.py
can_source/can_libs/std/game/__init__.py
can_source/can_libs/std/game/impl.py
can_source/can_libs/std/gui/__init__.py
can_source/can_libs/std/gui/impl.py
can_source/can_libs/std/https/__init__.py
can_source/can_libs/std/https/impl.py
can_source/can_libs/std/json/__init__.py
can_source/can_libs/std/json/impl.py
can_source/can_libs/std/macros/Py.cantonese
can_source/can_libs/std/macros/Rust.cantonese
can_source/can_libs/std/macros/math.cantonese
can_source/can_libs/std/macros/net.cantonese
can_source/can_libs/std/macros/sql.cantonese
can_source/can_libs/std/macros/std.cantonese
can_source/can_libs/std/macros/ui.cantonese
can_source/can_macros/impl.py
can_source/can_macros/macro.py
can_source/can_macros/match_state.py
can_source/can_macros/meta_var.py
can_source/can_macros/pat_matcher.py
can_source/can_macros/regex.py
can_source/can_parser/__init__.py
can_source/can_parser/parser_trait.py
can_source/can_parser/exp/exp_parser.py
Cantonese-1.0.10.dist-info/LICENSE
Cantonese-1.0.10.dist-info/METADATA
Cantonese-1.0.10.dist-info/WHEEL
Cantonese-1.0.10.dist-info/entry_points.txt
Cantonese-1.0.10.dist-info/top_level.txt
Cantonese-1.0.10.dist-info/RECORD
